{
  "version": "2.0",
  "envId": "rcwljy-5ghmq2ex26764978",
  "$schema": "https://framework-1258016615.tcloudbaseapp.com/schema/latest.json",
  "framework": {
    "name": "drone-training-system",
    "plugins": {
      "client": {
        "use": "@cloudbase/framework-plugin-website",
        "inputs": {
          "outputPath": "dist",
          "buildCommand": "npm run build",
          "cloudPath": "/",
          "websiteConfig": {
            "index": "index.html",
            "error": "index.html",
            "routes": [
              { "path": "/admin/*", "target": "admin/index.html" },
              { "path": "/admin", "target": "admin/index.html" },
              { "path": "/admin/login", "target": "admin/index.html" },
              { "path": "/admin/dashboard", "target": "admin/index.html" },
              { "path": "/courses/*", "target": "index.html" },
              { "path": "/course/*", "target": "index.html" },
              { "path": "/lesson/*", "target": "index.html" },
              { "path": "/exam/*", "target": "index.html" },
              { "path": "/my-learning", "target": "index.html" },
              { "path": "/checkout", "target": "index.html" },
              { "path": "/*", "target": "index.html" }
            ]
          }
        }
      },
      "functions": {
        "use": "@cloudbase/framework-plugin-function",
        "inputs": {
          "functions": [
            {
              "name": "admin",
              "timeout": 60,
              "memorySize": 256,
              "runtime": "Nodejs18.15",
              "handler": "index.main",
              "envVariables": {},
              "ignore": ["node_modules/**", ".git/**"],
              "triggers": []
            },
            {
              "name": "admin-http",
              "timeout": 60,
              "memorySize": 256,
              "runtime": "Nodejs18.15",
              "handler": "index.main",
              "envVariables": {},
              "ignore": ["node_modules/**", ".git/**"],
              "triggers": [
                { "name": "http-trigger", "type": "http" }
              ]
            },
            {
              "name": "api-admin",
              "timeout": 60,
              "memorySize": 256,
              "runtime": "Nodejs18.15",
              "handler": "index.main",
              "envVariables": {},
              "ignore": ["node_modules/**", ".git/**"],
              "triggers": [
                { "name": "http-trigger", "type": "http" }
              ]
            },
            {
              "name": "api-auth",
              "timeout": 60,
              "memorySize": 256,
              "runtime": "Nodejs18.15",
              "handler": "index.main",
              "envVariables": {},
              "ignore": ["node_modules/**", ".git/**"],
              "triggers": [
                { "name": "http-trigger", "type": "http" }
              ]
            },
            {
              "name": "api-course",
              "timeout": 60,
              "memorySize": 256,
              "runtime": "Nodejs18.15",
              "handler": "index.main",
              "envVariables": {},
              "ignore": ["node_modules/**", ".git/**"],
              "triggers": [
                { "name": "http-trigger", "type": "http" }
              ]
            },
            {
              "name": "api-exam",
              "timeout": 60,
              "memorySize": 256,
              "runtime": "Nodejs18.15",
              "handler": "index.main",
              "envVariables": {},
              "ignore": ["node_modules/**", ".git/**"],
              "triggers": [
                { "name": "http-trigger", "type": "http" }
              ]
            },
            {
              "name": "api-home",
              "timeout": 60,
              "memorySize": 256,
              "runtime": "Nodejs18.15",
              "handler": "index.main",
              "envVariables": {},
              "ignore": ["node_modules/**", ".git/**"],
              "triggers": [
                { "name": "http-trigger", "type": "http" }
              ]
            },
            {
              "name": "api-message",
              "timeout": 60,
              "memorySize": 256,
              "runtime": "Nodejs18.15",
              "handler": "index.main",
              "envVariables": {},
              "ignore": ["node_modules/**", ".git/**"],
              "triggers": [
                { "name": "http-trigger", "type": "http" }
              ]
            },
            {
              "name": "api-order",
              "timeout": 60,
              "memorySize": 256,
              "runtime": "Nodejs18.15",
              "handler": "index.main",
              "envVariables": {},
              "ignore": ["node_modules/**", ".git/**"],
              "triggers": [
                { "name": "http-trigger", "type": "http" }
              ]
            },
            {
              "name": "api-pay",
              "timeout": 60,
              "memorySize": 256,
              "runtime": "Nodejs18.15",
              "handler": "index.main",
              "envVariables": {},
              "ignore": ["node_modules/**", ".git/**"],
              "triggers": [
                { "name": "http-trigger", "type": "http" }
              ]
            },
            {
              "name": "api-shop",
              "timeout": 60,
              "memorySize": 256,
              "runtime": "Nodejs18.15",
              "handler": "index.main",
              "envVariables": {},
              "ignore": ["node_modules/**", ".git/**"],
              "triggers": [
                { "name": "http-trigger", "type": "http" }
              ]
            },
            {
              "name": "api-source",
              "timeout": 60,
              "memorySize": 256,
              "runtime": "Nodejs18.15",
              "handler": "index.main",
              "envVariables": {},
              "ignore": ["node_modules/**", ".git/**"],
              "triggers": [
                { "name": "http-trigger", "type": "http" }
              ]
            },
            {
              "name": "api-training",
              "timeout": 60,
              "memorySize": 256,
              "runtime": "Nodejs18.15",
              "handler": "index.main",
              "envVariables": {},
              "ignore": ["node_modules/**", ".git/**"],
              "triggers": [
                { "name": "http-trigger", "type": "http" }
              ]
            },
            {
              "name": "api-user",
              "timeout": 60,
              "memorySize": 256,
              "runtime": "Nodejs18.15",
              "handler": "index.main",
              "envVariables": {},
              "ignore": ["node_modules/**", ".git/**"],
              "triggers": [
                { "name": "http-trigger", "type": "http" }
              ]
            },
            {
              "name": "login-http",
              "timeout": 60,
              "memorySize": 256,
              "runtime": "Nodejs18.15",
              "handler": "index.main",
              "envVariables": {},
              "ignore": ["node_modules/**", ".git/**"],
              "triggers": [
                { "name": "http-trigger", "type": "http" }
              ]
            },
            {
              "name": "mobile-auth",
              "timeout": 60,
              "memorySize": 256,
              "runtime": "Nodejs18.15",
              "handler": "index.main",
              "envVariables": {},
              "ignore": ["node_modules/**", ".git/**"],
              "triggers": []
            },
            {
              "name": "mobile-course",
              "timeout": 60,
              "memorySize": 256,
              "runtime": "Nodejs18.15",
              "handler": "index.main",
              "envVariables": {},
              "ignore": ["node_modules/**", ".git/**"],
              "triggers": []
            },
            {
              "name": "mobile-exam",
              "timeout": 60,
              "memorySize": 256,
              "runtime": "Nodejs18.15",
              "handler": "index.main",
              "envVariables": {},
              "ignore": ["node_modules/**", ".git/**"],
              "triggers": []
            },
            {
              "name": "mobile-learning",
              "timeout": 60,
              "memorySize": 256,
              "runtime": "Nodejs18.15",
              "handler": "index.main",
              "envVariables": {},
              "ignore": ["node_modules/**", ".git/**"],
              "triggers": []
            },
            {
              "name": "mobile-order",
              "timeout": 60,
              "memorySize": 256,
              "runtime": "Nodejs18.15",
              "handler": "index.main",
              "envVariables": {},
              "ignore": ["node_modules/**", ".git/**"],
              "triggers": []
            },
            {
              "name": "submit-exam",
              "timeout": 60,
              "memorySize": 256,
              "runtime": "Nodejs18.15",
              "handler": "index.main",
              "envVariables": {},
              "ignore": ["node_modules/**", ".git/**"],
              "triggers": []
            },
            {
              "name": "wechat-pay",
              "timeout": 15,
              "memorySize": 256,
              "runtime": "Nodejs18.15",
              "handler": "index.main",
              "envVariables": {
                "WX_APPID": "",
                "WX_MCH_ID": "",
                "WX_API_KEY": "",
                "WX_NOTIFY_URL": ""
              },
              "ignore": ["node_modules/**", ".git/**"],
              "triggers": [
                { "name": "http-trigger", "type": "http" }
              ]
            },
            {
              "name": "migrate-permissions",
              "timeout": 60,
              "memorySize": 256,
              "runtime": "Nodejs18.15",
              "handler": "index.main",
              "envVariables": {},
              "ignore": ["node_modules/**", ".git/**"],
              "triggers": []
            },
            {
              "name": "init-source-data",
              "timeout": 60,
              "memorySize": 256,
              "runtime": "Nodejs18.15",
              "handler": "index.main",
              "envVariables": {},
              "ignore": ["node_modules/**", ".git/**"],
              "triggers": []
            },
            {
              "name": "web-api",
              "timeout": 60,
              "memorySize": 256,
              "runtime": "Nodejs18.15",
              "handler": "index.main",
              "envVariables": {},
              "ignore": ["node_modules/**", ".git/**"],
              "triggers": []
            },
            {
              "name": "api",
              "timeout": 60,
              "memorySize": 256,
              "runtime": "Nodejs18.15",
              "handler": "index.main",
              "envVariables": {},
              "ignore": ["node_modules/**", ".git/**"],
              "triggers": []
            }
          ]
        }
      }
    }
  }
}
